<?xml version="1.0" encoding="UTF-8" standalone="yes"?>
<items>
<item>
<title>[B][COLOR white]*  [/COLOR][COLOR yellow] Buscadores de fantasmas, 2x1 - el castillo Preston [Español]  [/COLOR][/B]</title>

<thumbnail>https://images-na.ssl-images-amazon.com/images/I/71BQm-aSGqL._AC_UL320_SR226,320_.jpg</thumbnail>  
<fanart>https://images-na.ssl-images-amazon.com/images/I/71BQm-aSGqL._AC_UL320_SR226,320_.jpg</fanart>
<urlsolve>https://www.youtube.com/watch?v=beMke0i_qUA</urlsolve>
</item>
<item>
<title>[B][COLOR white]* [/COLOR][COLOR yellow]  Buscadores de fantasmas, 2x2 - el castillo San Marcos [Español] [/COLOR][/B]</title>

<thumbnail>https://images-na.ssl-images-amazon.com/images/I/71BQm-aSGqL._AC_UL320_SR226,320_.jpg</thumbnail>  
<fanart>https://images-na.ssl-images-amazon.com/images/I/71BQm-aSGqL._AC_UL320_SR226,320_.jpg</fanart>
<urlsolve>https://www.youtube.com/watch?v=m4kBKRlVeeU</urlsolve>
</item>
<item>
<title>[B][COLOR white]* [/COLOR][COLOR yellow]  Buscadores de fantasmas, 2x3 - misión, La Purísima [Español] [/COLOR][/B]</title>

<thumbnail>https://images-na.ssl-images-amazon.com/images/I/71BQm-aSGqL._AC_UL320_SR226,320_.jpg</thumbnail>  
<fanart>https://images-na.ssl-images-amazon.com/images/I/71BQm-aSGqL._AC_UL320_SR226,320_.jpg</fanart>
<urlsolve>https://www.youtube.com/watch?v=YaRU6pGzjlY</urlsolve>
</item>
<item>
<title>[B][COLOR white]* [/COLOR][COLOR yellow]  Buscadores de fantasmas, 2x4 - la plantación Magnolia [Español]  [/COLOR][/B]</title>

<thumbnail>https://images-na.ssl-images-amazon.com/images/I/71BQm-aSGqL._AC_UL320_SR226,320_.jpg</thumbnail>  
<fanart>https://images-na.ssl-images-amazon.com/images/I/71BQm-aSGqL._AC_UL320_SR226,320_.jpg</fanart>
<urlsolve>https://www.youtube.com/watch?v=jkB5P-qgKBI</urlsolve>
</item>
<item>
<title>[B][COLOR white]* [/COLOR][COLOR yellow] Buscadores de fantasmas, 2x5 - el teatro Birdcage [Español]  [/COLOR][/B]</title>

<thumbnail>https://images-na.ssl-images-amazon.com/images/I/71BQm-aSGqL._AC_UL320_SR226,320_.jpg</thumbnail>  
<fanart>https://images-na.ssl-images-amazon.com/images/I/71BQm-aSGqL._AC_UL320_SR226,320_.jpg</fanart>
<urlsolve>https://www.youtube.com/watch?v=gEH2Px7VL_I</urlsolve>
</item>
<item>
<title>[B][COLOR white]* [/COLOR][COLOR yellow]  Buscadores de fantasmas, 2x6 - la cárcel de Eastern State [Español] [/COLOR][/B]</title>

<thumbnail>https://images-na.ssl-images-amazon.com/images/I/71BQm-aSGqL._AC_UL320_SR226,320_.jpg</thumbnail>  
<fanart>https://images-na.ssl-images-amazon.com/images/I/71BQm-aSGqL._AC_UL320_SR226,320_.jpg</fanart>
<urlsolve>https://www.youtube.com/watch?v=TthySYlCRko</urlsolve>
</item>
<item>
<title>[B][COLOR white]* [/COLOR][COLOR yellow]  Buscadores de Fantasmas, 2x7 La Cervecería Encantada.  [/COLOR][/B]</title>
<thumbnail>https://images-na.ssl-images-amazon.com/images/I/71BQm-aSGqL._AC_UL320_SR226,320_.jpg</thumbnail>  
<fanart>https://images-na.ssl-images-amazon.com/images/I/71BQm-aSGqL._AC_UL320_SR226,320_.jpg</fanart>
<urlsolve>https://www.youtube.com/watch?v=v_oEVNlu2RU</urlsolve>
</item>
<item>
<title>[B][COLOR white]* [/COLOR][COLOR yellow]  Buscadores de fantasmas, 2x8 - ancient Ram Inn [Español] [/COLOR][/B]</title>

<thumbnail>https://images-na.ssl-images-amazon.com/images/I/71BQm-aSGqL._AC_UL320_SR226,320_.jpg</thumbnail>  
<fanart>https://images-na.ssl-images-amazon.com/images/I/71BQm-aSGqL._AC_UL320_SR226,320_.jpg</fanart>
<urlsolve>https://www.youtube.com/watch?v=Qi_E5sqMi-0</urlsolve>
</item>
</items>