<item>
<title>[B]La Pantera Rosa T1[/B]</title>
<link>$doregex[makelist]</link>
<regex>
  <name>makelist</name>
  <listrepeat><![CDATA[
        <title>[COLOR white]  [makelist.param3][/COLOR] </title>
        <link>$doregex[getUrl]</link>
		<thumbnail>https://pics.filmaffinity.com/the_pink_panther_tv_series-644830390-large.jpg</thumbnail>
		<fanart>http://2.bp.blogspot.com/-Ff3gSlAUhKQ/Uz4ST3sQsTI/AAAAAAAACtg/jgpyFJl3_Ac/s1600/Imagen+principal.png</fanart>
        ]]></listrepeat>
<expres><![CDATA[href="\/.*,(.*?),list.*\n.*\n.*\n.*href="\/([^"]*)".*?>(.*?)<]]></expres>
<page>http://diskokosmiko.mx/Cuspide/la-pantera-rosa-t1-48234</page>
<cookieJar></cookieJar>
</regex>
<regex>
<name>getUrl</name>
<expres>DownloadUrl":"([^"]+)<expres>
<page>http://diskokosmiko.mx/action/DownloadFile?location=fi&amp;f=[makelist.param1]</page>
<rawpost>fileId=[makelist.param1]&amp;__RequestVerificationToken=$doregex[tok]</rawpost>
<referer>http://diskokosmiko.mx/[makelist.param2]</referer>
<connection>keep-alive</connection>
<accept>*/*</accept>
<X-Req>XMLHttpRequest</X-Req>
<cookieJar></cookieJar>
</regex>
<regex>
<name>tok</name>
<expres>DownloadFile.*RequestVerificationToken.*?value="([^"]+)<expres>
<page>http://diskokosmiko.mx/[makelist.param2]</page>
<referer>http://diskokosmiko.mx</referer>
<connection>keep-alive</connection>
<cookieJar></cookieJar>
</regex>
		<thumbnail>https://pics.filmaffinity.com/the_pink_panther_tv_series-644830390-large.jpg</thumbnail>
		<fanart>http://2.bp.blogspot.com/-Ff3gSlAUhKQ/Uz4ST3sQsTI/AAAAAAAACtg/jgpyFJl3_Ac/s1600/Imagen+principal.png</fanart>
</item>
<item>
<title>[B]La Pantera Rosa T2[/B]</title>
<link>$doregex[makelist]</link>
<regex>
  <name>makelist</name>
  <listrepeat><![CDATA[
        <title>[COLOR white]  [makelist.param3][/COLOR] </title>
        <link>$doregex[getUrl]</link>
		<thumbnail>https://pics.filmaffinity.com/the_pink_panther_tv_series-644830390-large.jpg</thumbnail>
		<fanart>http://2.bp.blogspot.com/-Ff3gSlAUhKQ/Uz4ST3sQsTI/AAAAAAAACtg/jgpyFJl3_Ac/s1600/Imagen+principal.png</fanart>
        ]]></listrepeat>
<expres><![CDATA[href="\/.*,(.*?),list.*\n.*\n.*\n.*href="\/([^"]*)".*?>(.*?)<]]></expres>
<page>http://diskokosmiko.mx/Cuspide/la-pantera-rosa-t2-48235</page>
<cookieJar></cookieJar>
</regex>
<regex>
<name>getUrl</name>
<expres>DownloadUrl":"([^"]+)<expres>
<page>http://diskokosmiko.mx/action/DownloadFile?location=fi&amp;f=[makelist.param1]</page>
<rawpost>fileId=[makelist.param1]&amp;__RequestVerificationToken=$doregex[tok]</rawpost>
<referer>http://diskokosmiko.mx/[makelist.param2]</referer>
<connection>keep-alive</connection>
<accept>*/*</accept>
<X-Req>XMLHttpRequest</X-Req>
<cookieJar></cookieJar>
</regex>
<regex>
<name>tok</name>
<expres>DownloadFile.*RequestVerificationToken.*?value="([^"]+)<expres>
<page>http://diskokosmiko.mx/[makelist.param2]</page>
<referer>http://diskokosmiko.mx</referer>
<connection>keep-alive</connection>
<cookieJar></cookieJar>
</regex>
		<thumbnail>https://pics.filmaffinity.com/the_pink_panther_tv_series-644830390-large.jpg</thumbnail>
		<fanart>http://2.bp.blogspot.com/-Ff3gSlAUhKQ/Uz4ST3sQsTI/AAAAAAAACtg/jgpyFJl3_Ac/s1600/Imagen+principal.png</fanart>
</item>
<item>
<title>[B]La Pantera Rosa T3[/B]</title>
<link>$doregex[makelist]</link>
<regex>
  <name>makelist</name>
  <listrepeat><![CDATA[
        <title>[COLOR white]  [makelist.param3][/COLOR] </title>
        <link>$doregex[getUrl]</link>
		<thumbnail>https://pics.filmaffinity.com/the_pink_panther_tv_series-644830390-large.jpg</thumbnail>
		<fanart>http://2.bp.blogspot.com/-Ff3gSlAUhKQ/Uz4ST3sQsTI/AAAAAAAACtg/jgpyFJl3_Ac/s1600/Imagen+principal.png</fanart>
        ]]></listrepeat>
<expres><![CDATA[href="\/.*,(.*?),list.*\n.*\n.*\n.*href="\/([^"]*)".*?>(.*?)<]]></expres>
<page>http://diskokosmiko.mx/Cuspide/la-pantera-rosa-t3-48236</page>
<cookieJar></cookieJar>
</regex>
<regex>
<name>getUrl</name>
<expres>DownloadUrl":"([^"]+)<expres>
<page>http://diskokosmiko.mx/action/DownloadFile?location=fi&amp;f=[makelist.param1]</page>
<rawpost>fileId=[makelist.param1]&amp;__RequestVerificationToken=$doregex[tok]</rawpost>
<referer>http://diskokosmiko.mx/[makelist.param2]</referer>
<connection>keep-alive</connection>
<accept>*/*</accept>
<X-Req>XMLHttpRequest</X-Req>
<cookieJar></cookieJar>
</regex>
<regex>
<name>tok</name>
<expres>DownloadFile.*RequestVerificationToken.*?value="([^"]+)<expres>
<page>http://diskokosmiko.mx/[makelist.param2]</page>
<referer>http://diskokosmiko.mx</referer>
<connection>keep-alive</connection>
<cookieJar></cookieJar>
</regex>
		<thumbnail>https://pics.filmaffinity.com/the_pink_panther_tv_series-644830390-large.jpg</thumbnail>
		<fanart>http://2.bp.blogspot.com/-Ff3gSlAUhKQ/Uz4ST3sQsTI/AAAAAAAACtg/jgpyFJl3_Ac/s1600/Imagen+principal.png</fanart>
</item>
<item>
<title>[B]La Pantera Rosa T4[/B]</title>
<link>$doregex[makelist]</link>
<regex>
  <name>makelist</name>
  <listrepeat><![CDATA[
        <title>[COLOR white]  [makelist.param3][/COLOR] </title>
        <link>$doregex[getUrl]</link>
		<thumbnail>https://pics.filmaffinity.com/the_pink_panther_tv_series-644830390-large.jpg</thumbnail>
		<fanart>http://2.bp.blogspot.com/-Ff3gSlAUhKQ/Uz4ST3sQsTI/AAAAAAAACtg/jgpyFJl3_Ac/s1600/Imagen+principal.png</fanart>
        ]]></listrepeat>
<expres><![CDATA[href="\/.*,(.*?),list.*\n.*\n.*\n.*href="\/([^"]*)".*?>(.*?)<]]></expres>
<page>http://diskokosmiko.mx/Cuspide/la-pantera-rosa-t4-48237</page>
<cookieJar></cookieJar>
</regex>
<regex>
<name>getUrl</name>
<expres>DownloadUrl":"([^"]+)<expres>
<page>http://diskokosmiko.mx/action/DownloadFile?location=fi&amp;f=[makelist.param1]</page>
<rawpost>fileId=[makelist.param1]&amp;__RequestVerificationToken=$doregex[tok]</rawpost>
<referer>http://diskokosmiko.mx/[makelist.param2]</referer>
<connection>keep-alive</connection>
<accept>*/*</accept>
<X-Req>XMLHttpRequest</X-Req>
<cookieJar></cookieJar>
</regex>
<regex>
<name>tok</name>
<expres>DownloadFile.*RequestVerificationToken.*?value="([^"]+)<expres>
<page>http://diskokosmiko.mx/[makelist.param2]</page>
<referer>http://diskokosmiko.mx</referer>
<connection>keep-alive</connection>
<cookieJar></cookieJar>
</regex>
		<thumbnail>https://pics.filmaffinity.com/the_pink_panther_tv_series-644830390-large.jpg</thumbnail>
		<fanart>http://2.bp.blogspot.com/-Ff3gSlAUhKQ/Uz4ST3sQsTI/AAAAAAAACtg/jgpyFJl3_Ac/s1600/Imagen+principal.png</fanart>
</item>