<?xml version="1.0" encoding="UTF-8" standalone="yes"?>
<item>
<title>[COLOR red]•[/COLOR] [COLOR white]TEMPORADA 1[/COLOR]</title>
<thumbnail>https://posterspy.com/wp-content/uploads/2015/09/mr-robot-oficial.jpg</thumbnail>
<fanart>https://pomowar.files.wordpress.com/2015/10/419.jpg</fanart>
<link>http://ignore</link>
</item>
<item>
<title>[COLOR white]01x01[/COLOR]</title>
<thumbnail>https://posterspy.com/wp-content/uploads/2015/09/mr-robot-oficial.jpg</thumbnail>
<fanart>https://pomowar.files.wordpress.com/2015/10/419.jpg</fanart> 
<link>http://alberto@209.126.108.87/series/Mr.%20Robot/Mr.%20Robot%20S01E01%20.mkv</link>                    
</item>
<item>
<title>[COLOR white]01x02[/COLOR]</title>
<thumbnail>https://posterspy.com/wp-content/uploads/2015/09/mr-robot-oficial.jpg</thumbnail>
<fanart>https://pomowar.files.wordpress.com/2015/10/419.jpg</fanart> 
<link>http://alberto@209.126.108.87/series/Mr.%20Robot/Mr.%20Robot%20S01E02%20.mkv</link>                    
</item>
<item>
<title>[COLOR white]01x03[/COLOR]</title>
<thumbnail>https://posterspy.com/wp-content/uploads/2015/09/mr-robot-oficial.jpg</thumbnail>
<fanart>https://pomowar.files.wordpress.com/2015/10/419.jpg</fanart> 
<link>http://alberto@209.126.108.87/series/Mr.%20Robot/Mr.%20Robot%20S01E03%20.mkv</link>                    
</item>
<item>
<title>[COLOR white]01x04[/COLOR]</title>
<thumbnail>https://posterspy.com/wp-content/uploads/2015/09/mr-robot-oficial.jpg</thumbnail>
<fanart>https://pomowar.files.wordpress.com/2015/10/419.jpg</fanart> 
<link>http://alberto@209.126.108.87/series/Mr.%20Robot/Mr.%20Robot%20S01E04%20.mkv</link>                    
</item>
<item>
<title>[COLOR white]01x05[/COLOR]</title>
<thumbnail>https://posterspy.com/wp-content/uploads/2015/09/mr-robot-oficial.jpg</thumbnail>
<fanart>https://pomowar.files.wordpress.com/2015/10/419.jpg</fanart> 
<link>http://alberto@209.126.108.87/series/Mr.%20Robot/Mr.%20Robot%20S01E05%20.mkv</link>                    
</item>
<item>
<title>[COLOR white]01x06[/COLOR]</title>
<thumbnail>https://posterspy.com/wp-content/uploads/2015/09/mr-robot-oficial.jpg</thumbnail>
<fanart>https://pomowar.files.wordpress.com/2015/10/419.jpg</fanart> 
<link>http://alberto@209.126.108.87/series/Mr.%20Robot/Mr.%20Robot%20S01E06%20.mkv</link>                    
</item>
<item>
<title>[COLOR white]01x07[/COLOR]</title>
<thumbnail>https://posterspy.com/wp-content/uploads/2015/09/mr-robot-oficial.jpg</thumbnail>
<fanart>https://pomowar.files.wordpress.com/2015/10/419.jpg</fanart> 
<link>http://alberto@209.126.108.87/series/Mr.%20Robot/Mr.%20Robot%20S01E07%20.mkv</link>                    
</item>
<item>
<title>[COLOR white]01x08[/COLOR]</title>
<thumbnail>https://posterspy.com/wp-content/uploads/2015/09/mr-robot-oficial.jpg</thumbnail>
<fanart>https://pomowar.files.wordpress.com/2015/10/419.jpg</fanart> 
<link>http://alberto@209.126.108.87/series/Mr.%20Robot/Mr.%20Robot%20S01E08%20%20.mkv</link>                    
</item>
<item>
<title>[COLOR white]01x09[/COLOR]</title>
<thumbnail>https://posterspy.com/wp-content/uploads/2015/09/mr-robot-oficial.jpg</thumbnail>
<fanart>https://pomowar.files.wordpress.com/2015/10/419.jpg</fanart> 
<link>http://alberto@209.126.108.87/series/Mr.%20Robot/Mr.%20Robot%20S01E09%20.mkv</link>                    
</item>
<item>
<title>[COLOR white]01x10[/COLOR]</title>
<thumbnail>https://posterspy.com/wp-content/uploads/2015/09/mr-robot-oficial.jpg</thumbnail>
<fanart>https://pomowar.files.wordpress.com/2015/10/419.jpg</fanart> 
<link>http://alberto@209.126.108.87/series/Mr.%20Robot/Mr.%20Robot%20S01E10%20.mkv</link>                    
</item>
 
