<?xml version="1.0" encoding="utf-8" standalone="yes"?>
<item>
<title>[B][COLOR white]TEMPORADA 1[/COLOR] [COLOR lime][HD][/COLOR][/B]</title>
<link>$doregex[makelist]</link>
<regex>
  <name>makelist</name>
  <listrepeat><![CDATA[
        <title>[makelist.param3]</title> 
        <link>$doregex[getUrl]</link>
<thumbnail>https://portadas.seriesgato.com/un-mundo-sin-fin-261656-p-200x294.jpg</thumbnail>
<fanart>http://ocio.levante-emv.com/img_contenido/noticias/2012/10/127789/2012_10_22_IMG_2012_10_22_123A453A34_mundo_3.jpg</fanart>
]]></listrepeat>
<expres><![CDATA[href="\/.*,(.*?),list.*\n.*\n.*\n.*href="\/([^"]*)".*?>(.*?)<]]></expres>
<page>http://diskokosmiko.mx/trivianita/un-mundo-sin-fin-70678</page>
<cookieJar></cookieJar>
</regex>
<regex>
<name>getUrl</name>
<expres>DownloadUrl":"([^"]+)<expres>
<page>http://diskokosmiko.mx/action/DownloadFile?location=fi&f=[makelist.param1]</page>
<rawpost>fileId=[makelist.param1]&__RequestVerificationToken=$doregex[tok]</rawpost>
<referer>http://diskokosmiko.mx/[makelist.param2]</referer>
<connection>keep-alive</connection>
<accept>*/*</accept>
<X-Req>XMLHttpRequest</X-Req>
<cookieJar></cookieJar>
</regex>
<regex>
<name>tok</name>
<expres>DownloadFile.*RequestVerificationToken.*?value="([^"]+)<expres>
<page>http://diskokosmiko.mx/[makelist.param2]</page>
<referer>http://diskokosmiko.mx</referer>
<connection>keep-alive</connection>
<cookieJar></cookieJar>
</regex>
<thumbnail>https://portadas.seriesgato.com/un-mundo-sin-fin-261656-p-200x294.jpg</thumbnail>
<fanart>http://ocio.levante-emv.com/img_contenido/noticias/2012/10/127789/2012_10_22_IMG_2012_10_22_123A453A34_mundo_3.jpg</fanart>
</item>